MANIFEST.in
README.md
setup.py
docs/Makefile
docs/conf.py
docs/index.rst
docs/introduction.rst
docs/make.bat
pyperclip/__init__.py
pyperclip.egg-info/PKG-INFO
pyperclip.egg-info/SOURCES.txt
pyperclip.egg-info/dependency_links.txt
pyperclip.egg-info/top_level.txt
tests/test_pyperclip.py